[
  {
    "industry": "其他未分類金屬製品製造業（2599）",
    "incident": "與有害物等之接觸（12）",
    "medium_type": "有害物（514）",
    "description": "罹災者陳○○為○○○工業社所僱挖土機操作人員，於112 年2 月1 日\n10 時30 分許，罹災者陳○○疑似因看到挖土機被○○○○股份有限公司\n吊掛入船艙內，故進入該船艙欲拆除吊鉤，於10 時55 分許，○○○○股\n份有限公司所僱督工欲準備開工作業，惟11 時10 分許找不到罹災者陳○\n○，後請大家協助尋找，最終由○○○○股份有限公司所僱吊掛作業人員\n發現罹災者陳○○昏倒於該船艙進出人孔下方之第2 層平臺上，經送醫急\n救後仍不治死亡。",
    "cause_analysis": "(一)直接原因：依臺灣臺中地方檢察署所提相驗資料、專家建議及事業單\n位諮詢結果所示，罹災者陳○○直接引起死亡之原因為窒\n息。 \n (二)間接原因： \n 不安全狀況： \n (1) 使勞工",
    "preventive_measures": "",
    "incident_type": "與有害物等之接觸",
    "incident_type_id": "12",
    "medium_type_general": "物質材料",
    "medium_type_general_id": "5",
    "medium_type_normal": "危險物, 有害物",
    "medium_type_normal_id": "51",
    "medium_type_specific": "有害物",
    "medium_type_specific_id": "514",
    "description_summary": "陳○○於船艙內拆除吊鉤時失蹤，後被發現昏倒於平臺，送醫不治死亡。",
    "cause_summary": "「勞工未架設必要設備、勞工未使用適當防護具、雇主未禁止不安全行為、雇主未辦理安全訓練、雇主未訂定安全規則」"
  }
]